[\n  {\n    "id": 789937531,\n    "timestamp": "20250903000358",\n    "button": "Num8",\n    "layer": 1,\n    "mode": "Wide",\n    "boundingBoxCount": 3,\n    "executionTime": 1172,\n    "category": "macro",\n    "severity": "unknown",\n    "perBoxSummary": "1xglare, 1xpartial_blockage, 1xsplashes"\n  },\n  {\n    "id": 789939062,\n    "timestamp": "20250903000400",\n    "button": "Num8",\n    "layer": 1,\n    "mode": "Wide",\n    "boundingBoxCount": 3,\n    "executionTime": 1172,\n    "category": "macro",\n    "severity": "unknown",\n    "perBoxSummary": "1xglare, 1xpartial_blockage, 1xsplashes"\n  },\n  {\n    "id": 789940281,\n    "timestamp": "20250903000401",\n    "button": "Num5",\n    "layer": 1,\n    "mode": "Wide",\n    "boundingBoxCount": 1,\n    "executionTime": 438,\n    "category": "macro",\n    "severity": "unknown",\n    "perBoxSummary": "1xsmudge"\n  },\n  {\n    "id": 789941546,\n    "timestamp": "20250903000402",\n    "button": "Num4",\n    "layer": 1,\n    "mode": "Wide",\n    "boundingBoxCount": 0,\n    "executionTime": 234,\n    "category": "json_profile",\n    "severity": "high",\n    "perBoxSummary": "JSON: Rain (High)"\n  },\n  {\n    "id": 789943218,\n    "timestamp": "20250903000404",\n    "button": "Num4",\n    "layer": 1,\n    "mode": "Wide",\n    "boundingBoxCount": 0,\n    "executionTime": 234,\n    "category": "json_profile",\n    "severity": "high",\n    "perBoxSummary": "JSON: Rain (High)"\n  },\n  {\n    "id": 789975937,\n    "timestamp": "20250903000437",\n    "button": "Num8",\n    "layer": 1,\n    "mode": "Wide",\n    "boundingBoxCount": 3,\n    "executionTime": 1172,\n    "category": "macro",\n    "severity": "unknown",\n    "perBoxSummary": "1xglare, 1xpartial_blockage, 1xsplashes"\n  },\n  {\n    "id": 789978328,\n    "timestamp": "20250903000439",\n    "button": "Num5",\n    "layer": 1,\n    "mode": "Wide",\n    "boundingBoxCount": 1,\n    "executionTime": 438,\n    "category": "macro",\n    "severity": "unknown",\n    "perBoxSummary": "1xsmudge"\n  },\n  {\n    "id": 789986562,\n    "timestamp": "20250903000447",\n    "button": "Num5",\n    "layer": 1,\n    "mode": "Wide",\n    "boundingBoxCount": 1,\n    "executionTime": 437,\n    "category": "macro",\n    "severity": "unknown",\n    "perBoxSummary": "1xsmudge"\n  },\n  {\n    "id": 789988875,\n    "timestamp": "20250903000450",\n    "button": "Num5",\n    "layer": 1,\n    "mode": "Wide",\n    "boundingBoxCount": 1,\n    "executionTime": 438,\n    "category": "macro",\n    "severity": "unknown",\n    "perBoxSummary": "1xsmudge"\n  },\n  {\n    "id": 790276671,\n    "timestamp": "20250903000938",\n    "button": "Num8",\n    "layer": 1,\n    "mode": "Wide",\n    "boundingBoxCount": 3,\n    "executionTime": 1171,\n    "category": "macro",\n    "severity": "unknown",\n    "perBoxSummary": "1xglare, 1xpartial_blockage, 1xsplashes"\n  },\n  {\n    "id": 790279171,\n    "timestamp": "20250903000940",\n    "button": "Num8",\n    "layer": 1,\n    "mode": "Wide",\n    "boundingBoxCount": 3,\n    "executionTime": 1171,\n    "category": "macro",\n    "severity": "unknown",\n    "perBoxSummary": "1xglare, 1xpartial_blockage, 1xsplashes"\n  },\n  {\n    "id": 790280000,\n    "timestamp": "20250903000941",\n    "button": "Num4",\n    "layer": 1,\n    "mode": "Wide",\n    "boundingBoxCount": 0,\n    "executionTime": 235,\n    "category": "json_profile",\n    "severity": "high",\n    "perBoxSummary": "JSON: Rain (High)"\n  },\n  {\n    "id": 818679156,\n    "timestamp": "20250903080300",\n    "button": "Num8",\n    "layer": 1,\n    "mode": "Wide",\n    "boundingBoxCount": 3,\n    "executionTime": 1172,\n    "category": "macro",\n    "severity": "unknown",\n    "perBoxSummary": "1xglare, 1xpartial_blockage, 1xsplashes"\n  },\n  {\n    "id": 818680578,\n    "timestamp": "20250903080301",\n    "button": "Num8",\n    "layer": 1,\n    "mode": "Wide",\n    "boundingBoxCount": 3,\n    "executionTime": 1172,\n    "category": "macro",\n    "severity": "unknown",\n    "perBoxSummary": "1xglare, 1xpartial_blockage, 1xsplashes"\n  },\n  {\n    "id": 818682500,\n    "timestamp": "20250903080303",\n    "button": "Num8",\n    "layer": 1,\n    "mode": "Wide",\n    "boundingBoxCount": 3,\n    "executionTime": 1172,\n    "category": "macro",\n    "severity": "unknown",\n    "perBoxSummary": "1xglare, 1xpartial_blockage, 1xsplashes"\n  },\n  {\n    "id": 818683312,\n    "timestamp": "20250903080304",\n    "button": "Num4",\n    "layer": 1,\n    "mode": "Wide",\n    "boundingBoxCount": 0,\n    "executionTime": 234,\n    "category": "json_profile",\n    "severity": "high",\n    "perBoxSummary": "JSON: Rain (High)"\n  },\n  {\n    "id": 818691187,\n    "timestamp": "20250903080312",\n    "button": "Num8",\n    "layer": 1,\n    "mode": "Wide",\n    "boundingBoxCount": 3,\n    "executionTime": 1172,\n    "category": "macro",\n    "severity": "unknown",\n    "perBoxSummary": "1xglare, 1xpartial_blockage, 1xsplashes"\n  },\n  {\n    "id": 818698109,\n    "timestamp": "20250903080319",\n    "button": "Num4",\n    "layer": 1,\n    "mode": "Wide",\n    "boundingBoxCount": 0,\n    "executionTime": 234,\n    "category": "json_profile",\n    "severity": "high",\n    "perBoxSummary": "JSON: Rain (High)"\n  },\n  {\n    "id": 862717562,\n    "timestamp": "20250903201658",\n    "button": "Num8",\n    "layer": 1,\n    "mode": "Wide",\n    "boundingBoxCount": 3,\n    "executionTime": 1172,\n    "category": "macro",\n    "severity": "unknown",\n    "perBoxSummary": "1xglare, 1xpartial_blockage, 1xsplashes"\n  }\n]